Mentera/__init__.py
Mentera/activation_functions.py
Mentera/nn_model.py
Mentera-1.0.dist-info/METADATA
Mentera-1.0.dist-info/WHEEL
Mentera-1.0.dist-info/top_level.txt
Mentera-1.0.dist-info/RECORD
