Metadata-Version: 2.1
Name: Mentera
Version: 1.0
Requires-Dist: numpy
